{
   "abstract" : "A wrapper for AT&T's Graphviz",
   "author" : [
      "Ron Savage <ron@savage.net.au>"
   ],
   "dynamic_config" : 1,
   "generated_by" : "Module::Build version 0.4005, CPAN::Meta::Converter version 2.131560",
   "license" : [
      "artistic_2"
   ],
   "meta-spec" : {
      "url" : "http://search.cpan.org/perldoc?CPAN::Meta::Spec",
      "version" : "2"
   },
   "name" : "GraphViz2",
   "prereqs" : {
      "build" : {
         "requires" : {
            "Test::More" : "0.94",
            "Test::Version" : "1.002003"
         }
      },
      "configure" : {
         "requires" : {
            "Module::Build" : "0.38"
         }
      },
      "runtime" : {
         "requires" : {
            "Algorithm::Dependency" : "1.11",
            "Algorithm::Dependency::Source::HoA" : "1.11",
            "Capture::Tiny" : "0.1",
            "Class::ISA" : "0.36",
            "Class::Load" : "0.17",
            "Config" : "0",
            "Config::Tiny" : "2.16",
            "DBI" : "1.616",
            "Data::Section::Simple" : "0.02",
            "Date::Simple" : "3.03",
            "File::Basename" : "2.77",
            "File::Copy" : "2.21",
            "File::HomeDir" : "0.99",
            "File::Slurp" : "9999.19",
            "File::Spec" : "3.4",
            "File::Temp" : "0.22",
            "File::Which" : "1.09",
            "HTML::Entities::Interpolate" : "1.04",
            "HTML::TreeBuilder" : "4.2",
            "HTTP::Tiny" : "0.012",
            "IPC::Run3" : "0.046",
            "Log::Handler" : "0.71",
            "Moo" : "1.002",
            "Parse::RecDescent" : "1.965001",
            "Perl6::Slurp" : "0.051003",
            "Scalar::Util" : "1.23",
            "Set::Array" : "0.23",
            "Text::Xslate" : "1.2",
            "Tree::DAG_Node" : "1.06",
            "Try::Tiny" : "0.09",
            "XML::Bare" : "0",
            "XML::Tiny" : "2.06",
            "charnames" : "0",
            "open" : "0",
            "parent" : "0.225",
            "strict" : "0",
            "utf8" : "0",
            "warnings" : "0"
         }
      }
   },
   "provides" : {
      "GraphViz2" : {
         "file" : "lib/GraphViz2.pm",
         "version" : "2.24"
      },
      "GraphViz2::Config" : {
         "file" : "lib/GraphViz2/Config.pm",
         "version" : "2.24"
      },
      "GraphViz2::DBI" : {
         "file" : "lib/GraphViz2/DBI.pm",
         "version" : "2.24"
      },
      "GraphViz2::Data::Grapher" : {
         "file" : "lib/GraphViz2/Data/Grapher.pm",
         "version" : "2.24"
      },
      "GraphViz2::Filer" : {
         "file" : "lib/GraphViz2/Filer.pm",
         "version" : "2.24"
      },
      "GraphViz2::Parse::ISA" : {
         "file" : "lib/GraphViz2/Parse/ISA.pm",
         "version" : "2.24"
      },
      "GraphViz2::Parse::RecDescent" : {
         "file" : "lib/GraphViz2/Parse/RecDescent.pm",
         "version" : "2.24"
      },
      "GraphViz2::Parse::Regexp" : {
         "file" : "lib/GraphViz2/Parse/Regexp.pm",
         "version" : "2.24"
      },
      "GraphViz2::Parse::STT" : {
         "file" : "lib/GraphViz2/Parse/STT.pm",
         "version" : "2.24"
      },
      "GraphViz2::Parse::XML" : {
         "file" : "lib/GraphViz2/Parse/XML.pm",
         "version" : "2.24"
      },
      "GraphViz2::Parse::Yacc" : {
         "file" : "lib/GraphViz2/Parse/Yacc.pm",
         "version" : "2.24"
      },
      "GraphViz2::Parse::Yapp" : {
         "file" : "lib/GraphViz2/Parse/Yapp.pm",
         "version" : "2.24"
      },
      "GraphViz2::Utils" : {
         "file" : "lib/GraphViz2/Utils.pm",
         "version" : "2.24"
      }
   },
   "release_status" : "stable",
   "resources" : {
      "license" : [
         "http://www.perlfoundation.org/artistic_license_2_0"
      ]
   },
   "version" : "2.24"
}
